./.gitignore
./.rich-codex.yml
./AGENTS.md
./CLAUDE.md
./PKG-INFO
./README.md
./justfile
./noxfile.py
./pyproject.toml
./uv.lock
./webology.py
./webology.tape
./img/pipx-run-webology.png
webology-2025.12.1.dist-info/METADATA
webology-2025.12.1.dist-info/WHEEL
webology-2025.12.1.dist-info/entry_points.txt
webology-2025.12.1.dist-info/RECORD
