Metadata-Version: 2.4
Name: webology
Version: 2025.12.1
Summary: My pypi/uvx card
Project-URL: Homepage, https://github.com/jefftriplett/webology
Project-URL: Code, https://github.com/jefftriplett/webology
Project-URL: Funding, https://github.com/users/jefftriplett/sponsorship
Project-URL: Issues, https://github.com/jefftriplett/webology/issues
Project-URL: Mastodon, https://mastodon.social/@webology
Project-URL: Twitter, https://twitter.com/webology
Project-URL: Django Job Board, https://djangojobboard.com
Author-email: Jeff Triplett <jeff.triplett@gmail.com>
License-Expression: Apache-2.0
Keywords: webology
Classifier: Development Status :: 5 - Production/Stable
Classifier: Intended Audience :: Developers
Classifier: License :: OSI Approved :: MIT License
Classifier: Natural Language :: English
Classifier: Operating System :: OS Independent
Classifier: Programming Language :: Python :: 3
Classifier: Programming Language :: Python :: 3 :: Only
Classifier: Programming Language :: Python :: 3.9
Classifier: Programming Language :: Python :: 3.10
Classifier: Programming Language :: Python :: 3.11
Classifier: Programming Language :: Python :: 3.12
Requires-Python: >=3.9
Requires-Dist: rich
Requires-Dist: typer
